LICENSE
MANIFEST.in
README.md
setup.cfg
setup.py
versioneer.py
pandoctools/__init__.py
pandoctools/__main__.py
pandoctools/_version.py
pandoctools/language_prefix.py
pandoctools/source-from-path
pandoctools.egg-info/PKG-INFO
pandoctools.egg-info/SOURCES.txt
pandoctools.egg-info/dependency_links.txt
pandoctools.egg-info/entry_points.txt
pandoctools.egg-info/requires.txt
pandoctools.egg-info/top_level.txt
pandoctools/cat_md/__init__.py
pandoctools/cat_md/__main__.py
pandoctools/cat_md/cat_md.py
pandoctools/cli/__init__.py
pandoctools/cli/__main__.py
pandoctools/cli/cli.py
pandoctools/pandoctools_resolve/__init__.py
pandoctools/pandoctools_resolve/__main__.py
pandoctools/pandoctools_resolve/resolve.py
pandoctools/ready/__init__.py
pandoctools/ready/__main__.py
pandoctools/ready/ready.py
pandoctools/regex_replace/__init__.py
pandoctools/regex_replace/cli.py
pandoctools/sh/Default
pandoctools/sh/Default.docx
pandoctools/sh/Default.html
pandoctools/sh/Default.sass
pandoctools/sh/Default.yml
pandoctools/sh/Default_args
pandoctools/sh/Default_ipynb_R.yml
pandoctools/sh/Default_ipynb_py3.yml
pandoctools/sh/Default_mathjax.html
pandoctools/sh/Default_pipe
pandoctools/sh/Default_prism.css
pandoctools/sh/Default_prism.js
pandoctools/sh/Defaults.ini
pandoctools/sh/Kiwi
pandoctools/sh/Kiwi.docx
pandoctools/sh/Kiwi.sass
pandoctools/sh/Kiwi.yml
pandoctools/sh/Kiwi_mathjax.html
pandoctools/sh/NotMarkdown
pandoctools/sh/NotMarkdown_pipe
pandoctools/sh/README.md
pandoctools/sh/Simple
pandoctools/sh/_bin_to_PATH
pandoctools/sh/_env_to_PATH
pandoctools/sh/_github_markdown.css
pandoctools/sh/_none
pandoctools/shared_vars/__init__.py
pandoctools/shared_vars/shared_vars.py