Metadata-Version: 2.1
Name: pandoctools
Version: 2.8.0.4
Summary: Profile manager of text processing pipelines: Pandoc filters, any text CLI filters. Atom+Markdown+Pandoc+Jupyter workflow, export to ipynb.
Home-page: https://github.com/kiwi0fruit/pandoctools
Author: Peter Zagubisalo
Author-email: peter.zagubisalo@gmail.com
License: MIT License
Platform: UNKNOWN
Classifier: Development Status :: 3 - Alpha
Classifier: Intended Audience :: Developers
Classifier: Topic :: Software Development :: Build Tools
Classifier: License :: OSI Approved :: MIT License
Classifier: Programming Language :: Python :: 3
Classifier: Programming Language :: Python :: 3.6
Requires-Python: >=3.6
